{
	"_comment": "Menu structure according to type of route. icons defined in ",
	"mapLabel": "14 september NOCACHE",
	"basemap": "OSM", 
	"mapCenterLonLat": [6.718139648437498,52.47357958606801],
	"mapZoom": 11,
	"rootDataDirectory": "./geodata/",
	"rootImageDirectory": "./images/",
	"menuheading": [
		{
			"heading": "Trains",
			"filenames": ["wpt_NS_NorthEast.gpx","wpt_BlauwNet.gpx","wpt_MerwedeLingelijnMap.gpx","wpt_NS_Northwest.gpx"],
			"labels": ["NS NE","BlaueNet","MerwedeLingelijn","NS NW"]
		},
		{
			"heading": "Overnight",
			"filenames": ["wpt_camping.gpx","wpt_huts.gpx"],
			"labels": ["Camping","Huts"]
		},
			{
			"heading": "POI",
			"filenames": ["wpt_poi_east.gpx"],
			"labels": ["east"]
		}
	]
}
